xgbrhomut/XGBPredict.py
xgbrhomut/__init__.py
xgbrhomut/models/R_xgb.sav
xgbrhomut/models/R_xgb_collapse.sav
xgbrhomut/models/R_xgb_collapse_dispersions.json
xgbrhomut/models/R_xgb_collapse_scaler.sav
xgbrhomut/models/R_xgb_dispersions.json
xgbrhomut/models/R_xgb_scaler.sav
xgbrhomut/models/__init__.py
xgbrhomut/models/ro_2_xgb.sav
xgbrhomut/models/ro_2_xgb_dispersions.json
xgbrhomut/models/ro_2_xgb_scaler.sav
xgbrhomut/models/ro_3_xgb_collapse.sav
xgbrhomut/models/ro_3_xgb_collapse_dispersions.json
xgbrhomut/models/ro_3_xgb_collapse_scaler.sav
xgbrhomut/r_mu_t/__init__.py
xgbrhomut/r_mu_t/ec8.py
xgbrhomut/r_mu_t/guerrini.py
xgbrhomut/r_mu_t/krawinkler_nassar.py
xgbrhomut/r_mu_t/miranda.py
xgbrhomut/r_mu_t/newmark_hall.py
xgbrhomut/r_mu_t/vidic.py
xgb_rhomut-1.3.0.dist-info/LICENSE
xgb_rhomut-1.3.0.dist-info/METADATA
xgb_rhomut-1.3.0.dist-info/WHEEL
xgb_rhomut-1.3.0.dist-info/top_level.txt
xgb_rhomut-1.3.0.dist-info/RECORD
