Metadata-Version: 2.1
Name: xgb-rhomut
Version: 1.3.0
Summary: Next-generation non-linear and collapse prediction pre-trained XGBoost models for short to long period systems.
Home-page: https://github.com/davitshahnazaryan3/XGB-rhomut
Author: Davit Shahnazaryan
Author-email: shahnazaryandavit1@gmail.com
License: GPL-3.0
Project-URL: Bug Tracker, https://github.com/davitshahnazaryan3/XGB-rhomut/issues
Classifier: License :: OSI Approved :: GNU General Public License v3 (GPLv3)
Classifier: Operating System :: OS Independent
Classifier: Programming Language :: Python :: 3
Classifier: Programming Language :: Python :: 3 :: Only
Requires-Python: >=3.8
License-File: LICENSE
Requires-Dist: joblib ~=1.2.0
Requires-Dist: numpy ~=1.24.2
Requires-Dist: pandas ~=1.5.0
Requires-Dist: scikit-learn ~=1.1.2
Requires-Dist: scipy ~=1.10.1
Requires-Dist: xgboost <=1.8,>=1.6
Requires-Dist: pydantic ~=1.10.4
Provides-Extra: dev
Requires-Dist: pytest ~=7.4.0 ; extra == 'dev'
Requires-Dist: schema ~=0.7.5 ; extra == 'dev'
Requires-Dist: flake8 ~=6.1.0 ; extra == 'dev'
